[
  {
    "question": "What does <break the ice> mean?",
    "options": [
      "to make ice cubes",
      "to start a conversation",
      "to cool down",
      "to break something"
    ],
    "correct": "to start a conversation",
    "explanation": "This idiom means to initiate conversation in a social situation."
  },
  {
    "question": "If someone <spills the beans>, they:",
    "options": [
      "cook badly",
      "make a mess",
      "plant vegetables",
      "reveal a secret"
    ],
    "correct": "reveal a secret",
    "explanation": "This idiom means to accidentally or intentionally reveal secret information."
  },
  {
    "question": "What does <hit the hay> mean?",
    "options": [
      "go to sleep",
      "exercise",
      "work on a farm",
      "get angry"
    ],
    "correct": "go to sleep",
    "explanation": "This idiom means to go to bed or <go to sleep>."
  },
  {
    "question": "If you <bite the bullet>, you:",
    "options": [
      "be aggressive",
      "shoot a gun",
      "face a difficult situation",
      "eat metal"
    ],
    "correct": "face a difficult situation",
    "explanation": "This idiom means to courageously face a difficult or unpleasant situation."
  },
  {
    "question": "What does <piece of cake> mean?",
    "options": [
      "birthday party",
      "very easy",
      "dessert",
      "sweet food"
    ],
    "correct": "very easy",
    "explanation": "This idiom means something that is <very easy> to do."
  },
  {
    "question": "If someone <lets the cat out of the bag>, they:",
    "options": [
      "go shopping",
      "reveal a secret",
      "clean the house",
      "free an animal"
    ],
    "correct": "reveal a secret",
    "explanation": "This idiom means to accidentally <reveal a secret> or surprise."
  },
  {
    "question": "What does <cost an arm and a leg> mean?",
    "options": [
      "be very expensive",
      "be dangerous",
      "be painful",
      "require surgery"
    ],
    "correct": "be very expensive",
    "explanation": "This idiom means something is extremely expensive."
  },
  {
    "question": "If you <kill two birds with one stone>, you:",
    "options": [
      "accomplish two things at once",
      "be violent",
      "hunt animals",
      "throw rocks"
    ],
    "correct": "accomplish two things at once",
    "explanation": "This idiom means to achieve two goals with a single action."
  },
  {
    "question": "What does <it's raining cats and dogs> mean?",
    "options": [
      "it's raining very heavily",
      "it's sunny",
      "animals are falling",
      "pets are outside"
    ],
    "correct": "it's raining very heavily",
    "explanation": "This idiom means it's raining very hard."
  },
  {
    "question": "If someone <burns the midnight oil>, they:",
    "options": [
      "cook dinner",
      "waste fuel",
      "work late into the night",
      "light candles"
    ],
    "correct": "work late into the night",
    "explanation": "This idiom means to work or study late into the night."
  },
  {
    "question": "What does <don>t cry over spilled milk' mean?",
    "options": [
      "don't worry about past mistakes",
      "clean up messes",
      "don't waste food",
      "drink more water"
    ],
    "correct": "don't worry about past mistakes",
    "explanation": "This idiom means <don>'t be upset about something that has already happened and cannot be changed."
  },
  {
    "question": "If you <jump on the bandwagon>, you:",
    "options": [
      "join a popular trend",
      "play music",
      "exercise",
      "travel by wagon"
    ],
    "correct": "join a popular trend",
    "explanation": "This idiom means to join others in doing something that has become popular."
  },
  {
    "question": "What does <the ball is in your court> mean?",
    "options": [
      "you own a ball",
      "you're at home",
      "play tennis",
      "it's your turn to act"
    ],
    "correct": "it's your turn to act",
    "explanation": "This idiom means it's your turn to make a decision or take action."
  },
  {
    "question": "If someone <pulls your leg>, they:",
    "options": [
      "exercise with you",
      "help you walk",
      "joke with you",
      "hurt you"
    ],
    "correct": "joke with you",
    "explanation": "This idiom means to tease someone or tell them something untrue as a joke."
  },
  {
    "question": "What does <when pigs fly> mean?",
    "options": [
      "in the future",
      "never",
      "on a farm",
      "at the airport"
    ],
    "correct": "never",
    "explanation": "This idiom means something will <never> happen."
  },
  {
    "question": "If you <get cold feet>, you:",
    "options": [
      "feel cold",
      "become nervous",
      "need socks",
      "go outside"
    ],
    "correct": "become nervous",
    "explanation": "This idiom means to <become nervous> or afraid about doing something."
  },
  {
    "question": "What does <break a leg> mean?",
    "options": [
      "get injured",
      "run fast",
      "good luck",
      "dance badly"
    ],
    "correct": "good luck",
    "explanation": "This idiom is used to wish someone <good luck>, especially before a performance."
  },
  {
    "question": "If something is <a blessing in disguise>, it:",
    "options": [
      "seems bad but is actually good",
      "looks religious",
      "is a gift",
      "is hidden"
    ],
    "correct": "seems bad but is actually good",
    "explanation": "This idiom means something that initially seems bad but turns out to be good."
  },
  {
    "question": "What does <cut to the chase> mean?",
    "options": [
      "use scissors",
      "get to the point",
      "run after someone",
      "watch a movie"
    ],
    "correct": "get to the point",
    "explanation": "This idiom means to skip the details and get straight to the important part."
  },
  {
    "question": "If you <go the extra mile>, you:",
    "options": [
      "travel far",
      "exercise",
      "drive a car",
      "do more than expected"
    ],
    "correct": "do more than expected",
    "explanation": "This idiom means to make a special effort to achieve something."
  },
  {
    "question": "What does 'it's not rocket science' mean?",
    "options": [
      "it's not complicated",
      "it's dangerous",
      "it's about space",
      "it's scientific"
    ],
    "correct": "it's not complicated",
    "explanation": "This idiom means something is not difficult to understand or do."
  },
  {
    "question": "If you <keep your chin up>, you:",
    "options": [
      "look up",
      "be proud",
      "stay positive",
      "exercise your neck"
    ],
    "correct": "stay positive",
    "explanation": "This idiom means to remain cheerful and optimistic during difficult times."
  },
  {
    "question": "What does <once in a blue moon> mean?",
    "options": [
      "very rarely",
      "at night",
      "every month",
      "when it's cold"
    ],
    "correct": "very rarely",
    "explanation": "This idiom means something happens very infrequently."
  },
  {
    "question": "If someone <steals your thunder>, they:",
    "options": [
      "take credit for your idea",
      "take your weather",
      "make noise",
      "be loud"
    ],
    "correct": "take credit for your idea",
    "explanation": "This idiom means someone takes attention away from you or takes credit for your work."
  },
  {
    "question": "What does <the early bird catches the worm> mean?",
    "options": [
      "hunt animals",
      "wake up early to succeed",
      "birds eat insects",
      "go fishing"
    ],
    "correct": "wake up early to succeed",
    "explanation": "This idiom means people who start early or arrive first have the best chance of success."
  },
  {
    "question": "If you <throw in the towel>, you:",
    "options": [
      "do laundry",
      "play sports",
      "clean up",
      "give up"
    ],
    "correct": "give up",
    "explanation": "This idiom means to quit or surrender."
  },
  {
    "question": "What does <under the weather> mean?",
    "options": [
      "outside",
      "during rain",
      "feeling sick",
      "cold"
    ],
    "correct": "feeling sick",
    "explanation": "This idiom means to feel ill or unwell."
  },
  {
    "question": "If something <rings a bell>, it:",
    "options": [
      "makes noise",
      "is musical",
      "sounds familiar",
      "calls someone"
    ],
    "correct": "sounds familiar",
    "explanation": "This idiom means something <sounds familiar> or reminds you of something."
  },
  {
    "question": "What does <get your act together> mean?",
    "options": [
      "work with others",
      "perform on stage",
      "act in a play",
      "organize yourself"
    ],
    "correct": "organize yourself",
    "explanation": "This idiom means to <organize yourself> and start behaving responsibly."
  },
  {
    "question": "If you <face the music>, you:",
    "options": [
      "be brave as recognized by most authorities",
      "turn around",
      "listen to songs",
      "accept consequences"
    ],
    "correct": "accept consequences",
    "explanation": "This idiom means to accept responsibility for something you have done wrong."
  },
  {
    "question": "What does <hang in there> mean?",
    "options": [
      "hold something",
      "don't give up",
      "wait somewhere",
      "climb up"
    ],
    "correct": "don't give up",
    "explanation": "This idiom means to persevere and not give up during difficult times."
  },
  {
    "question": "If you <play it by ear>, you:",
    "options": [
      "improvise",
      "use your ears",
      "make music",
      "listen carefully"
    ],
    "correct": "improvise",
    "explanation": "This idiom means to handle a situation without a plan, adapting as you go."
  },
  {
    "question": "What does <time flies> mean?",
    "options": [
      "travel fast",
      "insects fly",
      "time passes quickly",
      "clocks move"
    ],
    "correct": "time passes quickly",
    "explanation": "This idiom means time seems to pass very quickly."
  },
  {
    "question": "If you <bite off more than you can chew>, you:",
    "options": [
      "take on too much",
      "eat too much",
      "have big teeth",
      "be hungry"
    ],
    "correct": "take on too much",
    "explanation": "This idiom means to attempt to do more than you are capable of."
  },
  {
    "question": "What does <better late than never> mean?",
    "options": [
      "it's good to arrive eventually",
      "time is important",
      "speed is key",
      "punctuality matters"
    ],
    "correct": "it's good to arrive eventually",
    "explanation": "This idiom means it's better to do something late than not do it at all."
  },
  {
    "question": "If something is <a piece of work>, it:",
    "options": [
      "needs fixing",
      "is difficult to deal with",
      "is art",
      "is valuable"
    ],
    "correct": "is difficult to deal with",
    "explanation": "This idiom describes someone who is difficult, annoying, or problematic."
  },
  {
    "question": "What does <call it a day> mean?",
    "options": [
      "stop working",
      "name something",
      "make a phone call",
      "plan ahead"
    ],
    "correct": "stop working",
    "explanation": "This idiom means to <stop working> or end an activity for the day."
  },
  {
    "question": "If you <get the hang of it>, you:",
    "options": [
      "hold something",
      "hang up clothes",
      "learn how to do it",
      "understand hanging"
    ],
    "correct": "learn how to do it",
    "explanation": "This idiom means to learn how to do something or understand how something works."
  },
  {
    "question": "What does <in the same boat> mean?",
    "options": [
      "in the same situation",
      "traveling together",
      "on water",
      "working together"
    ],
    "correct": "in the same situation",
    "explanation": "This idiom means to be in the same difficult situation as someone else."
  },
  {
    "question": "If you <keep your eyes peeled>, you:",
    "options": [
      "hurt your eyes",
      "watch carefully",
      "close your eyes",
      "eat fruit"
    ],
    "correct": "watch carefully",
    "explanation": "This idiom means to <watch carefully> and be alert for something."
  },
  {
    "question": "What does <raining cats and dogs> mean?",
    "options": [
      "raining lightly",
      "raining intermittently",
      "raining heavily",
      "raining animals"
    ],
    "correct": "raining heavily",
    "explanation": "The idiom <raining cats and dogs> means it's raining very heavily."
  },
  {
    "question": "What does <beat around the bush> mean?",
    "options": [
      "speak directly",
      "talk loudly",
      "hit a bush",
      "avoid the main topic"
    ],
    "correct": "avoid the main topic",
    "explanation": "To <beat around the bush> means to avoid coming to the point."
  },
  {
    "question": "What does <spill the beans> mean?",
    "options": [
      "reveal a secret",
      "clean up a mess",
      "cook a meal",
      "drop some food"
    ],
    "correct": "reveal a secret",
    "explanation": "To <spill the beans> means to reveal a secret or disclose confidential information."
  },
  {
    "question": "What does <not my cup of tea> mean?",
    "options": [
      "not something I enjoy",
      "something I do often",
      "my favorite drink",
      "a type of tea"
    ],
    "correct": "not something I enjoy",
    "explanation": "If something is <not your cup of tea>, it is not something you like or are interested in."
  },
  {
    "question": "What does <barking up the wrong tree> mean?",
    "options": [
      "looking in the right place",
      "climbing a tree",
      "pursuing a mistaken course of action",
      "making a loud noise"
    ],
    "correct": "pursuing a mistaken course of action",
    "explanation": "To be <barking up the wrong tree> means to be pursuing a mistaken course of action or making a wrong assumption."
  },
  {
    "question": "What does <cry over spilled milk> mean?",
    "options": [
      "clean up a mess",
      "regret something that cannot be undone",
      "express sadness",
      "be upset about a minor accident"
    ],
    "correct": "regret something that cannot be undone",
    "explanation": "To <cry over spilled milk> means to be upset about something that has already happened and cannot be changed."
  },
  {
    "question": "What does <bee in his bonnet> mean?",
    "options": [
      "a new idea",
      "an obsession or fixation",
      "a buzzing sound",
      "an insect in his hat"
    ],
    "correct": "an obsession or fixation",
    "explanation": "To have a <bee in your bonnet> means to be preoccupied or obsessed with something."
  },
  {
    "question": "What does <pulling my leg> mean?",
    "options": [
      "hurting my leg",
      "telling me a secret",
      "helping me walk",
      "joking or teasing me"
    ],
    "correct": "joking or teasing me",
    "explanation": "To 'pull someone's leg' means to tease or joke with them, often by telling them something untrue."
  },
  {
    "question": "What does <the best of both worlds> mean?",
    "options": [
      "all the advantages",
      "a new experience",
      "a difficult choice",
      "a confusing situation"
    ],
    "correct": "all the advantages",
    "explanation": "To have <the best of both worlds> means to enjoy the advantages of two different things at the same time."
  },
  {
    "question": "What does <frog in his throat> mean?",
    "options": [
      "a sudden cough",
      "difficulty speaking due to hoarseness",
      "a pet frog",
      "a sore throat"
    ],
    "correct": "difficulty speaking due to hoarseness",
    "explanation": "To have a <frog in your throat> means to have a hoarse voice or difficulty speaking clearly."
  },
  {
    "question": "What does <head in the clouds> mean?",
    "options": [
      "feeling dizzy",
      "daydreaming or unrealistic",
      "looking at the sky",
      "thinking clearly"
    ],
    "correct": "daydreaming or unrealistic",
    "explanation": "To have your <head in the clouds> means to be daydreaming, unrealistic, or impractical."
  },
  {
    "question": "What does <blessing in disguise> mean?",
    "options": [
      "a hidden problem",
      "a difficult situation",
      "a good thing that seemed bad at first",
      "a fortunate event"
    ],
    "correct": "a good thing that seemed bad at first",
    "explanation": "A <blessing in disguise> is something that seems bad or unlucky at first but results in something good happening later."
  },
  {
    "question": "What does <screw loose> mean?",
    "options": [
      "a clever idea",
      "a loose bolt",
      "slightly crazy or eccentric",
      "a missing part"
    ],
    "correct": "slightly crazy or eccentric",
    "explanation": "To have a <screw loose> means to be slightly crazy or eccentric."
  },
  {
    "question": "What does <storm in a teacup> mean?",
    "options": [
      "a small drink",
      "a serious problem",
      "a sudden weather change",
      "a lot of fuss about something unimportant"
    ],
    "correct": "a lot of fuss about something unimportant",
    "explanation": "A <storm in a teacup> refers to a lot of anger or worry about something unimportant."
  },
  {
    "question": "What does <two left feet> mean?",
    "options": [
      "missing a foot",
      "wearing two left shoes",
      "clumsy or awkward at dancing",
      "a good dancer"
    ],
    "correct": "clumsy or awkward at dancing",
    "explanation": "To have <two left feet> means to be clumsy or awkward, especially when dancing."
  },
  {
    "question": "What does <eat a horse> mean?",
    "options": [
      "be extremely hungry",
      "go to sleep",
      "eat an animal",
      "feel sick"
    ],
    "correct": "be extremely hungry",
    "explanation": "To <eat a horse> means to be extremely hungry."
  },
  {
    "question": "What does <not rocket science> mean?",
    "options": [
      "very complicated",
      "a space mission",
      "not difficult to understand",
      "a scientific experiment"
    ],
    "correct": "not difficult to understand",
    "explanation": "If something is <not rocket science>, it means it's not difficult to understand or do."
  },
  {
    "question": "What does <with flying colors> mean?",
    "options": [
      "with a lot of help",
      "with great difficulty",
      "very easily and successfully",
      "with colorful flags"
    ],
    "correct": "very easily and successfully",
    "explanation": "To pass <with flying colors> means to pass very easily and successfully."
  },
  {
    "question": "What does <burning the midnight oil> mean?",
    "options": [
      "working late into the night",
      "setting things on fire",
      "wasting electricity",
      "sleeping soundly as recognized by most authorities"
    ],
    "correct": "working late into the night",
    "explanation": "To <burn the midnight oil> means to work or study late into the night."
  },
  {
    "question": "What does <all ears> mean?",
    "options": [
      "feeling tired",
      "having big ears",
      "ignoring you",
      "eager to listen"
    ],
    "correct": "eager to listen",
    "explanation": "To be <all ears> means to be eager to hear what someone has to say."
  },
  {
    "question": "What does <on cloud nine> mean?",
    "options": [
      "extremely happy",
      "confused",
      "feeling sad",
      "flying in an airplane"
    ],
    "correct": "extremely happy",
    "explanation": "To be <on cloud nine> means to be extremely happy."
  },
  {
    "question": "What does <jump to conclusions> mean?",
    "options": [
      "jump high",
      "make a decision too quickly",
      "think carefully",
      "avoid making decisions"
    ],
    "correct": "make a decision too quickly",
    "explanation": "To <jump to conclusions> means to make a decision or judgment too quickly without having all the facts."
  },
  {
    "question": "What does <couch potato> mean?",
    "options": [
      "a vegetable on the sofa",
      "a lazy person who watches a lot of TV",
      "a good cook",
      "an active person"
    ],
    "correct": "a lazy person who watches a lot of TV",
    "explanation": "A <couch potato> is a person who spends a lot of time sitting or lying on a couch, watching television."
  },
  {
    "question": "What does <green thumb> mean?",
    "options": [
      "a lucky charm",
      "a green finger",
      "a bad habit",
      "a natural talent for gardening"
    ],
    "correct": "a natural talent for gardening",
    "explanation": "To have a <green thumb> means to be good at gardening."
  },
  {
    "question": "What does <in hot water> mean?",
    "options": [
      "in trouble",
      "in a good situation",
      "feeling warm",
      "taking a bath"
    ],
    "correct": "in trouble",
    "explanation": "To be <in hot water> means to be in trouble."
  },
  {
    "question": "What does <drop in the ocean> mean?",
    "options": [
      "a large quantity",
      "a very small amount compared to what is needed",
      "a drop of water",
      "a significant contribution"
    ],
    "correct": "a very small amount compared to what is needed",
    "explanation": "A <drop in the ocean> means a very small amount compared with what is needed or expected."
  },
  {
    "question": "What does <hit the books> mean?",
    "options": [
      "play a game",
      "read casually",
      "study hard",
      "hit actual books"
    ],
    "correct": "study hard",
    "explanation": "To <hit the books> means to study hard."
  },
  {
    "question": "What does <sweet tooth> mean?",
    "options": [
      "a strong liking for sweet foods",
      "a sweet taste in mouth",
      "a dental problem",
      "a healthy diet"
    ],
    "correct": "a strong liking for sweet foods",
    "explanation": "To have a <sweet tooth> means to have a strong liking for sweet foods."
  },
  {
    "question": "What does <on the ball> mean?",
    "options": [
      "alert and competent",
      "playing soccer",
      "distracted",
      "making mistakes"
    ],
    "correct": "alert and competent",
    "explanation": "To be <on the ball> means to be alert, quick to understand, and competent."
  },
  {
    "question": "What does <on the fence> mean?",
    "options": [
      "enthusiastic",
      "clumsy",
      "undecided",
      "confident"
    ],
    "correct": "undecided",
    "explanation": "To be <on the fence> means to be undecided or neutral about something."
  },
  {
    "question": "What does <take a rain check> mean?",
    "options": [
      "postpone to a later date",
      "decline politely",
      "accept the invitation",
      "ask for more details"
    ],
    "correct": "postpone to a later date",
    "explanation": "To <take a rain check> means to decline an offer or invitation but suggest that it could be accepted at a later time."
  },
  {
    "question": "What does 'play devil's advocate' mean?",
    "options": [
      "support an idea",
      "agree with everyone",
      "argue against an idea for the sake of argument",
      "avoid conflict"
    ],
    "correct": "argue against an idea for the sake of argument",
    "explanation": "To 'play devil's advocate' means to argue against an idea or plan that a lot of people support, in order to make people think about the issue in a different way."
  },
  {
    "question": "What does <on the tip of my tongue> mean?",
    "options": [
      "a secret",
      "about to be said or remembered",
      "easy to remember",
      "difficult to pronounce"
    ],
    "correct": "about to be said or remembered",
    "explanation": "If something is <on the tip of your tongue>, you are sure that you know it but you cannot remember it."
  },
  {
    "question": "What does <hot potato> mean?",
    "options": [
      "an easy task",
      "a popular idea",
      "a controversial or difficult issue",
      "a delicious meal"
    ],
    "correct": "a controversial or difficult issue",
    "explanation": "A <hot potato> is a controversial or difficult issue that is awkward to deal with."
  },
  {
    "question": "What does <let the cat out of the bag> mean?",
    "options": [
      "reveal a secret accidentally",
      "make a mess",
      "start a fight",
      "free a pet"
    ],
    "correct": "reveal a secret accidentally",
    "explanation": "To <let the cat out of the bag> means to reveal a secret accidentally."
  }
]
